ctapipe_io_nectarcam/__init__.py
ctapipe_io_nectarcam/_version.py
ctapipe_io_nectarcam/anyarray_dtypes.py
ctapipe_io_nectarcam/calibration.py
ctapipe_io_nectarcam/constants.py
ctapipe_io_nectarcam/containers.py
ctapipe_io_nectarcam/version.py
ctapipe_io_nectarcam/resources/NectarCam-003.camgeom.fits.gz
ctapipe_io_nectarcam/resources/Pulse_template_nectarCam_17042020.dat
ctapipe_io_nectarcam/resources/calibrationfile_run3255_pedrun3255_gainrun3155.hdf5
ctapipe_io_nectarcam/resources/calibrationfile_run3255_pedrun3255_gainrun3155_ctapipe018.hdf5
ctapipe_io_nectarcam/tests/test_nectarcameventsource.py
ctapipe_io_nectarcam/tests/test_trigger_patches.py
ctapipe_io_nectarcam/tests/test_version.py
ctapipe_io_nectarcam-0.2.2.dist-info/licenses/LICENSE.md
ctapipe_io_nectarcam-0.2.2.dist-info/METADATA
ctapipe_io_nectarcam-0.2.2.dist-info/WHEEL
ctapipe_io_nectarcam-0.2.2.dist-info/entry_points.txt
ctapipe_io_nectarcam-0.2.2.dist-info/top_level.txt
ctapipe_io_nectarcam-0.2.2.dist-info/RECORD
