Metadata-Version: 2.4
Name: ctapipe_io_nectarcam
Version: 0.2.2
Summary: ctapipe plugin for reading NectarCam files
Author: NectarCAM collaboration
License: BSD-3-Clause
Project-URL: Bug Tracker, https://github.com/cta-observatory/ctapipe_io_nectarcam/issues
Project-URL: Source Code, https://github.com/cta-observatory/ctapipe_io_nectarcam
Classifier: Development Status :: 3 - Alpha
Classifier: License :: OSI Approved :: BSD License
Classifier: Intended Audience :: Science/Research
Classifier: Topic :: Scientific/Engineering :: Astronomy
Classifier: Topic :: Scientific/Engineering :: Physics
Classifier: Programming Language :: Python :: 3 :: Only
Classifier: Programming Language :: Python :: 3.10
Classifier: Programming Language :: Python :: 3.11
Requires-Python: >=3.10
License-File: LICENSE.md
Requires-Dist: ctapipe~=0.24.0
Requires-Dist: protozfits
Requires-Dist: scipy
Provides-Extra: test
Requires-Dist: pytest; extra == "test"
Requires-Dist: pytest-cov; extra == "test"
Requires-Dist: pytest-xdist; extra == "test"
Provides-Extra: dev
Requires-Dist: setuptools_scm; extra == "dev"
Provides-Extra: all
Requires-Dist: ctapipe_io_nectarcam[dev,test]; extra == "all"
Dynamic: license-file
